{
  "bruh": "bruh",

  "fuck": "language","shit": "language","cunt": "language","bitch": "language",
  "fag": "language","whore": "language","nigga": "language","nigger": "language",
  "slut": "language",
  "ass": "ass",

  "lol": "auto_react","ew": "auto_react","wow": "auto_react","lmao": "auto_react",
  "LMAO": "auto_react","LOL": "auto_react","wtf": "auto_react","ok": "auto_react",
  "no": "auto_react","O:": "auto_react","love": "auto_react", "nice": "auto_react",
  "cool": "auto_react","heart": "auto_react","haha": "auto_react","whoa": "auto_react",
  "woah": "auto_react","sad": "auto_react","ugh": "auto_react","nah": "auto_react",
  "okay": "auto_react","oof": "auto_react","oeuf": "auto_react", "good": "auto_react",
  "yea": "auto_react","ya": "auto_react","yeah": "auto_react","wows": "auto_react",
  "truck": "auto_react","sadness": "auto_react","omg": "auto_react","concur": "auto_react",
  "agree": "auto_react","disagree": "auto_react",";-;": "auto_react","angry": "auto_react",
  "mad": "auto_react","laugh": "auto_react","yes": "auto_react",":(": "auto_react",
  ":)": "auto_react","):": "auto_react","(:": "auto_react",":O": "auto_react",
  "</3": "auto_react","cry": "auto_react","rip": "auto_react",

  "bot": "called","dentaku": "called"
}
